Metadata-Version: 1.0
Name: dici
Version: 0.4.1
Summary: easy to use dict replacement
Home-page: UNKNOWN
Author: Rodney Gomes
Author-email: rodneygomes@gmail.com
License: Apache 2.0 License
Platform: UNKNOWN
